alu/src/alu.v
`timescale 1ns/1ns
module alu #(
  parameter N = 8
)
(
  input      [N-1:0]  A       ,
  input      [N-1:0]  B       ,
  input      [3:0]    sel     ,
  output reg [N-1:0]  result  ,
  output reg          overflow,
  output reg          zero    ,
  output reg          negative
);

  always @(*) begin
	overflow = 0;
	zero = 0;
	negative = 0; 
    case (sel) 
      4'b0000: {overflow,result} = A + B;
      4'b0001: {overflow,result} = A - B;
   // 4'b0010: sum = A * B; // mult and div must be design seperate
   // 4'b0011: sum = A /B;
      4'b0100: result = A & B;
      4'b0101: result = A | B;
      4'b0110: result = ~(A & B);
      4'b0111: result = ~(A | B);
      4'b1000: result = A ^ B;
      4'b1001: result = ~(A ^ B);
      4'b1010: result = ~A;
      default: result = 0;
    endcase
    if (result == 0) zero = 1;
    else zero = 0;
    if (result[7] == 1) negative = 1;
    else negative = 0;
  end

endmodule

alu/tb/alu_tb.sv
/* verilator lint_off WIDTHTRUNC */
`timescale 1ns/1ns
module alu_tb ();
  parameter N = 8;
  reg [N-1:0] A,B;
  reg [3:0] sel;
  wire [N-1:0] result;
  wire overflow, negative, zero;

  initial begin
    $dumpfile ("wave.vcd");
    $dumpvars (0,dut);
  end

  alu dut (
    .A        (A)       ,
    .B        (B)       ,
    .sel      (sel)     ,
    .result   (result)  ,
    .overflow (overflow),
    .negative (negative),
    .zero     (zero)
  );

  initial begin 
    for (int i = 0; i < 10; i = i + 1) begin 
      sel = i;
      A = $random ();
      B = $random ();
      #1;
      $display ("A = %b, B = %b, sel = %b,overflow = %b, result = %b, zero = %b, negative = %b/n", A, B, sel , overflow, result, zero, negative);
    end
    $finish;
  end
  
 endmodule

alu/sim/wave.vcd
$version Generated by VerilatedVcd $end
$timescale 1ns $end
 $scope module $rootio $end
 $upscope $end
 $scope module alu_tb $end
  $var wire 32 + N [31:0] $end
  $var wire 8 # A [7:0] $end
  $var wire 8 $ B [7:0] $end
  $var wire 4 % sel [3:0] $end
  $var wire 8 & result [7:0] $end
  $var wire 1 ' overflow $end
  $var wire 1 ( negative $end
  $var wire 1 ) zero $end
  $scope module dut $end
   $var wire 32 + N [31:0] $end
   $var wire 8 # A [7:0] $end
   $var wire 8 $ B [7:0] $end
   $var wire 4 % sel [3:0] $end
   $var wire 8 & result [7:0] $end
   $var wire 1 ' overflow $end
   $var wire 1 ) zero $end
   $var wire 1 ( negative $end
  $upscope $end
  $scope module unnamedblk1 $end
   $var wire 32 * i [31:0] $end
  $upscope $end
 $upscope $end
$enddefinitions $end


#0
b11111100 #
b11111111 $
b0000 %
b11111011 &
1'
1(
0)
b00000000000000000000000000000000 *
b00000000000000000000000000001000 +
#1
b11111111 #
b00111111 $
b0001 %
b11000000 &
0'
b00000000000000000000000000000001 *
#2
b00110110 #
b10100010 $
b0010 %
b00000000 &
0(
1)
b00000000000000000000000000000010 *
#3
b10101100 #
b00001011 $
b0011 %
b00000000000000000000000000000011 *
#4
b11010000 #
b00001100 $
b0100 %
b00000000000000000000000000000100 *
#5
b11111110 #
b00001001 $
b0101 %
b11111111 &
1(
0)
b00000000000000000000000000000101 *
#6
b10010100 #
b10110001 $
b0110 %
b01101111 &
0(
b00000000000000000000000000000110 *
#7
b10100101 #
b00000110 $
b0111 %
b01011000 &
b00000000000000000000000000000111 *
#8
b00010111 #
b11100011 $
b1000 %
b11110100 &
1(
b00000000000000000000000000001000 *
#9
b10100101 #
b11001000 $
b1001 %
b10010010 &
b00000000000000000000000000001001 *
#10
b00000000000000000000000000001010 *
