demux1_8/src/demux1_8.v
`timescale 1ns/1ns
module demux1_8 (
  input       y,
  input [2:0] sel,
  output reg  i0,i1,i2,i3,i4,i5,i6,i7 
);
 
  always @(*) begin
    i0 = 0;
    i1 = 0;
    i2 = 0;
    i3 = 0;
    i4 = 0;
    i5 = 0;
    i6 = 0;
    i7 = 0;
    case (sel)
      3'b000: i0 = y;
      3'b001: i1 = y;
      3'b010: i2 = y;
      3'b011: i3 = y;
      3'b100: i4 = y;
      3'b101: i5 = y;
      3'b110: i6 = y;
      3'b111: i7 = y;
      default: begin 
        i0 = 0;
        i1 = 0;
        i2 = 0;
        i3 = 0;
        i4 = 0;
        i5 = 0;
        i6 = 0;
        i7 = 0;
      end
    endcase
  end

endmodule

demux1_8/tb/demux1_8_tb.v
`timescale 1ns/1ns
module demux1_8_tb();
  wire i0,i1,i2,i3,i4,i5,i6,i7;
  reg [2:0] sel;
  reg y;
  reg [7:0] result;
 
  initial begin
    $dumpfile ("wave.vcd");
    $dumpvars (0,dut);
  end

  assign result = {i7,i6,i5,i4,i3,i2,i1,i0};

  demux1_8 dut(
    .i0   (i0)  ,
    .i1   (i1)  ,
    .i2   (i2)  ,
    .i3   (i3)  ,
    .i4   (i4)  ,
    .i5   (i5)  ,
    .i6   (i6)  ,
    .i7   (i7)  ,
    .sel  (sel) ,
    .y    (y)
  );

  initial begin
    $display ("Start Simulate...");

    sel = 3'b000; y = 1; 
    #10;
    if (result == 8'b00000001) $display ("PASSED i0"); else $error;

    sel = 3'b001; y = 1; 
    #10;
    if (result == 8'b00000010) $display ("PASSED i1"); else $error;
 
    sel = 3'b010; y = 1;
    #10; 
    if (result == 8'b00000100) $display ("PASSED i2"); else $error;
 
     sel = 3'b011; y = 1;
    #10; 
    if (result == 8'b00001000) $display ("PASSED i3"); else $error;
   
     sel = 3'b100; y = 1;
    #10; 
    if (result == 8'b00010000) $display ("PASSED i4"); else $error;
   
     sel = 3'b101; y = 1; 
   #10;
    if (result == 8'b00100000) $display ("PASSED i5"); else $error;
    
    sel = 3'b110; y = 1; 
    #10;
    if (result == 8'b01000000) $display ("PASSED i6"); else $error;
    
     sel = 3'b111; y = 1;
    #10; 
    if (result == 8'b10000000) $display ("PASSED i7"); else $error;

    $display ("Done simulate"); 
    $stop;
    end

 endmodule

demux1_8/sim/wave.vcd
$version Generated by VerilatedVcd $end
$timescale 1ns $end
 $scope module $rootio $end
 $upscope $end
 $scope module demux1_8_tb $end
  $var wire 1 # i0 $end
  $var wire 1 $ i1 $end
  $var wire 1 % i2 $end
  $var wire 1 & i3 $end
  $var wire 1 ' i4 $end
  $var wire 1 ( i5 $end
  $var wire 1 ) i6 $end
  $var wire 1 * i7 $end
  $var wire 3 , sel [2:0] $end
  $var wire 1 - y $end
  $var wire 8 + result [7:0] $end
  $scope module dut $end
   $var wire 1 - y $end
   $var wire 3 , sel [2:0] $end
   $var wire 1 # i0 $end
   $var wire 1 $ i1 $end
   $var wire 1 % i2 $end
   $var wire 1 & i3 $end
   $var wire 1 ' i4 $end
   $var wire 1 ( i5 $end
   $var wire 1 ) i6 $end
   $var wire 1 * i7 $end
  $upscope $end
 $upscope $end
$enddefinitions $end


#0
1#
0$
0%
0&
0'
0(
0)
0*
b00000001 +
b000 ,
1-
#10
0#
1$
b00000010 +
b001 ,
#20
0$
1%
b00000100 +
b010 ,
#30
0%
1&
b00001000 +
b011 ,
#40
0&
1'
b00010000 +
b100 ,
#50
0'
1(
b00100000 +
b101 ,
#60
0(
1)
b01000000 +
b110 ,
#70
0)
1*
b10000000 +
b111 ,
