encoder8_3/src/encoder8_3.v
`timescale 1ns/1ns
/* verilator lint_off WIDTHTRUNC */
module encoder8_3 #( 
  parameter WIDTH = 8,
            WIDTH_OUT = 3
)
(
  input  [WIDTH-1:0]    D,
  output            reg x,
  output            reg y,
  output            reg z
);

  // 
  logic [WIDTH_OUT-1:0] Q;
  assign {x,y,z} = Q;

  always @(*) begin
	Q = 0; 
    for (int i = 0; i < WIDTH; i = i + 1) begin 
      if (D[i]) begin 
        Q = i;
      end
    end
  end

 endmodule

encoder8_3/tb/encoder8_3_tb.v
`timescale 1ns/1ns
/* verilator lint_off WIDTHEXPAND */
module encoder8_3_tb ();
  wire x,y,z;
  reg [7:0] D;
  
  initial begin 
    $dumpfile ("wave.vcd");
    $dumpvars (0,dut);
  end

  encoder8_3 dut (
    .D (D),
    .x (x),
    .y (y),
    .z (z)
  );

  initial begin
    for (int j = 0; j < 8; j = j + 1) begin 
      D = 1 << j;
      #5;
      assert ({x,y,z} == j) $display ("PASSED");
      else  $display ("FAILED at x = %b, y = %b, z = %b ", x, y, z);
    end
  end

endmodule

encoder8_3/sim/wave.vcd
$version Generated by VerilatedVcd $end
$timescale 1ns $end
 $scope module $rootio $end
 $upscope $end
 $scope module encoder8_3_tb $end
  $var wire 1 # x $end
  $var wire 1 $ y $end
  $var wire 1 % z $end
  $var wire 8 ( D [7:0] $end
  $scope module dut $end
   $var wire 32 * WIDTH [31:0] $end
   $var wire 32 + WIDTH_OUT [31:0] $end
   $var wire 8 ( D [7:0] $end
   $var wire 1 # x $end
   $var wire 1 $ y $end
   $var wire 1 % z $end
   $var wire 3 & Q [2:0] $end
   $scope module unnamedblk1 $end
    $var wire 32 ' i [31:0] $end
   $upscope $end
  $upscope $end
  $scope module unnamedblk1 $end
   $var wire 32 ) j [31:0] $end
  $upscope $end
 $upscope $end
$enddefinitions $end


#0
0#
0$
0%
b000 &
b00000000000000000000000000001000 '
b00000001 (
b00000000000000000000000000000000 )
b00000000000000000000000000001000 *
b00000000000000000000000000000011 +
#5
1%
b001 &
b00000010 (
b00000000000000000000000000000001 )
#10
1$
0%
b010 &
b00000100 (
b00000000000000000000000000000010 )
#15
1%
b011 &
b00001000 (
b00000000000000000000000000000011 )
#20
1#
0$
0%
b100 &
b00010000 (
b00000000000000000000000000000100 )
#25
1%
b101 &
b00100000 (
b00000000000000000000000000000101 )
#30
1$
0%
b110 &
b01000000 (
b00000000000000000000000000000110 )
#35
1%
b111 &
b10000000 (
b00000000000000000000000000000111 )
#40
b00000000000000000000000000001000 )
