decoder3_8/src/decoder3_8.v
`timescale 1ns/1ns
module decoder3_8 #(
  parameter WIDTH_IN = 3,
            WIDTH_OUT = 8
)
( 
  input       [WIDTH_IN-1:0]  A_in,
  output reg  [WIDTH_OUT-1:0] Y_out
);
  
  assign Y_out =  (1'b1 << A_in); 

 endmodule

decoder3_8/tb/decoder3_8_tb.v
`timescale 1ns/1ns
/* verilator lint_off WIDTHTRUNC */
module decoder3_8_tb ();
  parameter WIDTH_IN = 3,
            WIDTH_OUT = 8;

  wire [WIDTH_OUT-1:0] Y_out;
  reg  [WIDTH_IN-1:0] A_in;

  initial begin 
    $dumpfile ("wave.vcd");
    $dumpvars (0,dut);
  end

  decoder3_8 #(
    .WIDTH_IN   (WIDTH_IN),
    .WIDTH_OUT  (WIDTH_OUT)
  ) dut (
    .A_in   (A_in),
    .Y_out  (Y_out)
  );

  initial begin 
    $display ("Starting simulate...");
    A_in = 3'b000; 
    #1;
    if (Y_out == 8'b00000001)  $display ("Passed Result Y = %b",Y_out); 
    else $error;
    #10;
    //
    A_in = 3'b001; 
    #1;
    if (Y_out == 8'b00000010)  $display ("Passed Result Y = %b",Y_out); 
    else $error;
    #10;
    //
    A_in = 3'b010; 
    #1;
    if (Y_out == 8'b00000100)  $display ("Passed Result Y = %b",Y_out); 
    else $error;
    #10;
    //
    A_in = 3'b011; 
    #1;
    if (Y_out == 8'b00001000)  $display ("Passed Result Y = %b",Y_out); 
    else $error;
    #10;
    //
    A_in = 3'b100; 
    #1;
    if (Y_out == 8'b00010000)  $display ("Passed Result Y = %b",Y_out); 
    else $error;
    #10;
    //
    A_in = 3'b101; 
    #1;
    if (Y_out == 8'b00100000)  $display ("Passed Result Y = %b",Y_out); 
    else $error;
    #10;
    //
    A_in = 3'b110; 
    #1;
    if (Y_out == 8'b01000000)  $display ("Passed Result Y = %b",Y_out); 
    else $error;
    #10;
    //
    A_in = 3'b111; 
    #1;
    if (Y_out == 8'b10000000)  $display ("Passed Result Y = %b",Y_out); 
    else $error;
    #10;
  $stop;
  end
endmodule

decoder3_8/sim/wave.vcd
$version Generated by VerilatedVcd $end
$timescale 1ns $end
 $scope module $rootio $end
 $upscope $end
 $scope module decoder3_8_tb $end
  $var wire 32 % WIDTH_IN [31:0] $end
  $var wire 32 & WIDTH_OUT [31:0] $end
  $var wire 8 # Y_out [7:0] $end
  $var wire 3 $ A_in [2:0] $end
  $scope module dut $end
   $var wire 32 % WIDTH_IN [31:0] $end
   $var wire 32 & WIDTH_OUT [31:0] $end
   $var wire 3 $ A_in [2:0] $end
   $var wire 8 # Y_out [7:0] $end
  $upscope $end
 $upscope $end
$enddefinitions $end


#0
b00000001 #
b000 $
b00000000000000000000000000000011 %
b00000000000000000000000000001000 &
#1
#11
b00000010 #
b001 $
#12
#22
b00000100 #
b010 $
#23
#33
b00001000 #
b011 $
#34
#44
b00010000 #
b100 $
#45
#55
b00100000 #
b101 $
#56
#66
b01000000 #
b110 $
#67
#77
b10000000 #
b111 $
